<tt xml:lang="English" xmlns="http://www.w3.org/ns/ttml">
 <head>
  <metadata xmlns:ttm="http://www.w3.org/ns/ttml#metadata">
   <ttm:title>031813_factor_talkingpts.asf</ttm:title>
  </metadata>
 </head>
 <body>
  <div>
   <p xml:id="1" begin="00:00:00.000" end="00:00:01.368">>> Bill: HI, I'M BILL O'REILLY.</p>
   <p xml:id="2" begin="00:00:01.368" end="00:00:02.936">THANKS FOR WATCHING US TONIGHT.</p>
   <p xml:id="3" begin="00:00:02.936" end="00:00:04.938">IS AMERICA STILL THE LAND OF OPPORTUNITY?</p>
   <p xml:id="4" begin="00:00:04.938" end="00:00:07.707">THAT IS THE SUBJECT OF THIS EVENING'S TALKING POINTS</p>
   <p xml:id="5" begin="00:00:07.707" end="00:00:10.744">MEMO. AS ALERT AMERICANS WELL</p>
   <p xml:id="6" begin="00:00:10.744" end="00:00:12.212">KNOW, PRESIDENT OBAMA IS TRYING TO FUNDAMENTALLY</p>
   <p xml:id="7" begin="00:00:12.212" end="00:00:14.748">CHANGE THE U.S.A. HE SEES OUR SYSTEM AS</p>
   <p xml:id="8" begin="00:00:14.748" end="00:00:17.450">BASICALLY UNFAIR. AND WANTS TO PROVIDE MORE</p>
   <p xml:id="9" begin="00:00:17.450" end="00:00:17.451">SERVICES AND MONEY TO THOSE</p>
   <p xml:id="10" begin="00:00:18.752" end="00:00:22.589">WHO DON'T HAVE VERY MUCH. THE REPUBLICAN PARTY SAYS</p>
   <p xml:id="11" begin="00:00:22.589" end="00:00:25.058">THE PRESIDENT'S SOCIAL JUSTICE OUTLOOK IS DAMAGING</p>
   <p xml:id="12" begin="00:00:25.058" end="00:00:26.960">THE FREEZING RAIN STRUCTURE OF THE COUNTRY.</p>
   <p xml:id="13" begin="00:00:26.960" end="00:00:29.763">HIGH TAXATION AND HIGH DEBT ARE HOLDING BACK THE</p>
   <p xml:id="14" begin="00:00:29.763" end="00:00:32.132">ECONOMY AND THE G.O.P. BELIEVES MR. OBAMA IS</p>
   <p xml:id="15" begin="00:00:32.132" end="00:00:36.469">CREATING A NATION AT WAR WITH ITSELF.</p>
   <p xml:id="16" begin="00:00:36.469" end="00:00:36.470">THE AFFLUENT VS. THE</p>
   <p xml:id="17" begin="00:00:38.538" end="00:00:40.140">NONAFFLUENT. OVER THE WEEKEND SENATOR</p>
   <p xml:id="18" begin="00:00:40.140" end="00:00:42.542">TED CRUZE OF TEXAS, A CONSERVATIVE, DELIVERED A</p>
   <p xml:id="19" begin="00:00:42.542" end="00:00:46.012">VERY EMOTIONAL SPEECH AT CPAC.</p>
   <p xml:id="20" begin="00:00:46.012" end="00:00:48.615">>> MY FATHER CAME FROM CUBA.</p>
   <p xml:id="21" begin="00:00:48.615" end="00:00:51.484">HE HAD BEEN IN PRISON. HE HAD BEEN TORTURED IN</p>
   <p xml:id="22" begin="00:00:51.484" end="00:00:51.485">CUBA.</p>
   <p xml:id="23" begin="00:00:51.918" end="00:00:56.656">AND HE CAME TO TEXAS WITH NOTHING, WITH 100 IN HIS</p>
   <p xml:id="24" begin="00:00:56.656" end="00:00:59.292">UNDERWEAR. DIDN'T SPEAK A WORD OF</p>
   <p xml:id="25" begin="00:00:59.292" end="00:01:01.694">ENGLISH. WASHED DISHES MAKING 50</p>
   <p xml:id="26" begin="00:01:01.694" end="00:01:11.503">CENTS AN HOUR. IN SOMEONE HAD CAME UP TO</p>
   <p xml:id="27" begin="00:01:11.503" end="00:01:13.939">THAT 18-YEAR-OLD KID AVENUE AS HE WAS WASHING DISHES</p>
   <p xml:id="28" begin="00:01:13.939" end="00:01:18.710">AND SUGGESTED TO HIM THAT 55 YEARS HENCE HIS SON</p>
   <p xml:id="29" begin="00:01:18.710" end="00:01:21.813">WOULD BE SWORN INTO OFFICE AS A UNITED STATES SENATOR</p>
   <p xml:id="30" begin="00:01:21.813" end="00:01:23.548">REPRESENTING THE GREAT STATE OF TEXAS.</p>
   <p xml:id="31" begin="00:01:23.548" end="00:01:29.354">[ APPLAUSE ] THAT WOULD HAVE BEEN</p>
   <p xml:id="32" begin="00:01:29.354" end="00:01:31.690">UNIMAGINABLE. >> NOW MR. CRUZE SAYS HIS</p>
   <p xml:id="33" begin="00:01:31.690" end="00:01:34.359">DAD MADE IT ON HIS OWN WITHOUT GOVERNMENT</p>
   <p xml:id="34" begin="00:01:34.359" end="00:01:35.660">ASSISTANCE. HE WORKED HARD AND PROVIDE</p>
   <p xml:id="35" begin="00:01:35.660" end="00:01:37.896">FOR HIS FAMILY AND NOW HIS SON HAS ACHIEVED THE</p>
   <p xml:id="36" begin="00:01:37.896" end="00:01:40.398">AMERICAN DREAM. THAT'S THE WAY THIS COUNTRY</p>
   <p xml:id="37" begin="00:01:40.398" end="00:01:43.735">IS SUPPOSED TO WORK. BUT PRESIDENT OBAMA HIMSELF</p>
   <p xml:id="38" begin="00:01:43.735" end="00:01:45.871">HAS A VERY COMPELLING STORY TO TELL.</p>
   <p xml:id="39" begin="00:01:45.871" end="00:01:49.040">HIS FATHER ABANDONED HIM. HE WAS RAISED PRIMARILY BY</p>
   <p xml:id="40" begin="00:01:49.040" end="00:01:50.942">HIS MATERNAL GRANDPARENTS IN HAWAII.</p>
   <p xml:id="41" begin="00:01:50.942" end="00:01:53.745">HE HAD FEW RESOURCES. YET, BARACK OBAMA ROSE UP</p>
   <p xml:id="42" begin="00:01:53.745" end="00:01:56.047">TO BECOME THE MOST POWERFUL MAN IN THE WORLD, A</p>
   <p xml:id="43" begin="00:01:56.047" end="00:01:59.217">STUNNING ACHIEVEMENT. HOW MUCH THE SYSTEM HELPED</p>
   <p xml:id="44" begin="00:01:59.217" end="00:02:02.087">MR. OBAMA IS UNKNOWN AS HIS COLLEGE RECORDS HAVE BEEN</p>
   <p xml:id="45" begin="00:02:02.087" end="00:02:05.824">KEPT PRIVATE. WE DON'T KNOW THE EXTENT OF</p>
   <p xml:id="46" begin="00:02:05.824" end="00:02:08.660">AFFIRMATIVE ACTION. WE DON'T KNOW HOW MUCH THE</p>
   <p xml:id="47" begin="00:02:08.660" end="00:02:10.595">GOVERNMENT SUBSIDIZED HIS CLIMB TO THE TOP.</p>
   <p xml:id="48" begin="00:02:10.595" end="00:02:13.131">IT WOULD BE VERY HELPFUL TO HAVE THAT INFORMATION</p>
   <p xml:id="49" begin="00:02:13.131" end="00:02:18.970">SIMPLY TO BE FAIR TO THE PRESIDENT AND HIS VISION</p>
   <p xml:id="50" begin="00:02:18.970" end="00:02:22.374">THERE IS NO PRESIDENT OBAMA BELIEVES HIS DISCUSS IS IS</p>
   <p xml:id="51" begin="00:02:22.374" end="00:02:25.110">DUE TO GOVERNMENT THAT GOES TO THE FAMOUS LINE "YOU</p>
   <p xml:id="52" begin="00:02:25.110" end="00:02:28.013">DIDN'T BUILD THAT." SO THE BATTLE LINES ARE NOW</p>
   <p xml:id="53" begin="00:02:28.013" end="00:02:30.015">DRAWN BETWEEN SENATOR CRUISE WHO BELIEVES IN THE</p>
   <p xml:id="54" begin="00:02:30.015" end="00:02:32.651">FREE MARKET AND SMALL GOVERNMENT AND PRESIDENT</p>
   <p xml:id="55" begin="00:02:32.651" end="00:02:34.920">OBAMA WHO WANTS THE GOVERNMENT PARTIALLY</p>
   <p xml:id="56" begin="00:02:34.920" end="00:02:39.057">REGULATE THE ECONOMY AND IS TRYING TO IMPOSE A GIANT</p>
   <p xml:id="57" begin="00:02:39.057" end="00:02:40.525">CO-LOSS US IS IN WASHINGTON.</p>
   <p xml:id="58" begin="00:02:40.525" end="00:02:42.894">THAT'S THE STRUGGLE THAT WE THE AMERICAN PEOPLE ARE</p>
   <p xml:id="59" begin="00:02:42.894" end="00:02:45.730">ENDURING RIGHT NOW. IN THE END THERE WILL BE NO</p>
   <p xml:id="60" begin="00:02:45.730" end="00:02:47.632">COMPROMISE. ONE SIDE OR THE OTHER IS</p>
   <p xml:id="61" begin="00:02:47.632" end="00:02:51.536">GOING TO HAVE TO PREVAIL AND THAT'S THE MEMO.</p>
   <p xml:id="62" begin="00:02:51.536" end="00:02:54.406">TOP STORY TONIGHT REACTION JOINING US FROM WASHINGTON</p>
   <p xml:id="63" begin="00:02:54.406" end="00:02:56.441">IS MARY KATHARINEHAM AND JUAN WILLIAMS BOTH A FOX</p>
   <p xml:id="64" begin="00:02:56.441" end="00:02:58.743">NEWS ANALYST. JUAN, I ASSUME YOU ARE ON</p>
   <p xml:id="65" begin="00:02:58.743" end="-3787960:-1:-24.255">THE BIG GOVERNMENT SIDE. >> YOU ARE RIGHT</p>
  </div>
 </body>
</tt>
