<?xml version="1.0" encoding="UTF-8"?>
<tt xml:lang="en" xmlns="http://www.w3.org/ns/ttml">
 <head>
  <metadata xmlns:ttm="http://www.w3.org/ns/ttml#metadata">
   <ttm:title>ccdata</ttm:title>
  </metadata>
 </head>
 <body>
  <div>
   <p xml:id="1" begin="00:00:06.519" end="00:00:08.654">&gt;&gt;&gt; IN THE PERSONAL STORY<br/></p>
   <p xml:id="2" begin="00:00:07.153" end="00:00:10.189">SEGMENT TONIGHT, IS THE NEW<br/></p>
   <p xml:id="3" begin="00:00:08.788" end="00:00:11.257">ANTHONY WEINER SEXTING<br/></p>
   <p xml:id="4" begin="00:00:10.322" end="00:00:13.826">SCANDAL FAIR GAME IN THE<br/></p>
   <p xml:id="5" begin="00:00:11.390" end="00:00:15.127">PRESIDENTIAL CAMPAIGN?<br/></p>
   <p xml:id="6" begin="00:00:13.959" end="00:00:17.663">WEINER, OF COURSE, IS<br/></p>
   <p xml:id="7" begin="00:00:15.261" end="00:00:19.665">CURRENTLY THE HUSBAND OF TOP<br/></p>
   <p xml:id="8" begin="00:00:17.797" end="00:00:19.999">HILLARY CLINTON AIDE HUMA<br/></p>
   <p xml:id="9" begin="00:00:19.799" end="00:00:20.966">ABEDIN.<br/></p>
   <p xml:id="10" begin="00:00:20.132" end="00:00:23.836">ABEDIN ANNOUNCED YESTERDAY<br/></p>
   <p xml:id="11" begin="00:00:21.100" end="00:00:25.137">THAT SHE IS CELEBRATING FROM<br/></p>
   <p xml:id="12" begin="00:00:23.969" end="00:00:25.871">WEINER FOLLOWING NEWS OF HIS<br/></p>
   <p xml:id="13" begin="00:00:25.271" end="00:00:27.139">LATEST SCANDAL.<br/></p>
   <p xml:id="14" begin="00:00:26.005" end="00:00:28.974">DONALD TRUMP WASTED LITTLE<br/></p>
   <p xml:id="15" begin="00:00:27.273" end="00:00:30.509">TIME JUMPING ON THIS STORY.<br/></p>
   <p xml:id="16" begin="00:00:29.108" end="00:00:32.278">&gt;&gt; IN THE CASE OF ANTHONY<br/></p>
   <p xml:id="17" begin="00:00:30.643" end="00:00:35.514">WEINER SHE IS MARRIED TO A<br/></p>
   <p xml:id="18" begin="00:00:32.411" end="00:00:35.981">GUY WHO IS UNCONTROLLED AND<br/></p>
   <p xml:id="19" begin="00:00:35.648" end="00:00:38.350">UNCONTROLLABLE.<br/></p>
   <p xml:id="20" begin="00:00:36.115" end="00:00:40.986">HE IS A SICK PERSON AND, YOU<br/></p>
   <p xml:id="21" begin="00:00:38.484" end="00:00:42.788">KNOW, SHE HAS ACCESS TO<br/></p>
   <p xml:id="22" begin="00:00:41.120" end="00:00:45.257">CLASSIFIED INFORMATION.<br/></p>
   <p xml:id="23" begin="00:00:42.922" end="00:00:46.592">HUMA ABEDIN HAS ACCESS TO<br/></p>
   <p xml:id="24" begin="00:00:45.391" end="00:00:47.860">CLASSIFIED INFORMATION.<br/></p>
   <p xml:id="25" begin="00:00:46.725" end="00:00:49.595">HOW HILLARY GOT AWAY WITH<br/></p>
   <p xml:id="26" begin="00:00:47.993" end="00:00:49.895">THAT ONE, NOBODY WILL EVER<br/></p>
   <p xml:id="27" begin="00:00:49.728" end="00:00:52.832">KNOW.<br/></p>
   <p xml:id="28" begin="00:00:50.029" end="00:00:55.601">BUT, TO THINK THAT IT'S VERY<br/></p>
   <p xml:id="29" begin="00:00:52.965" end="00:00:56.268">LIKELY THAT MUCH OF THIS<br/></p>
   <p xml:id="30" begin="00:00:55.734" end="00:00:57.703">INFORMATION ANTHONY WEINER<br/></p>
   <p xml:id="31" begin="00:00:56.402" end="00:00:59.905">WOULD KNOW ABOUT.<br/></p>
   <p xml:id="32" begin="00:00:57.837" end="00:01:00.539">&gt;&gt; THE CLINTON CAMPAIGN<br/></p>
   <p xml:id="33" begin="00:01:00.039" end="00:01:01.707">RESPONDING TO THE CHARGE<br/></p>
   <p xml:id="34" begin="00:01:00.673" end="00:01:03.509">THIS WAY:<br/></p>
   <p xml:id="35" begin="00:01:01.841" end="00:01:04.477">&gt;&gt; TO THE SUBSTANCE OF WHAT<br/></p>
   <p xml:id="36" begin="00:01:03.642" end="00:01:06.579">DONALD TRUMP SAID, IT'S<br/></p>
   <p xml:id="37" begin="00:01:04.610" end="00:01:07.613">ANOTHER ONE OF THE<br/></p>
   <p xml:id="38" begin="00:01:06.712" end="00:01:08.214">OUTLANDISH THING THIS MAN<br/></p>
   <p xml:id="39" begin="00:01:07.746" end="00:01:09.748">TOSSES ABOUT.<br/></p>
   <p xml:id="40" begin="00:01:08.347" end="00:01:12.151">AND HE REPEATED IT IT'S THE<br/></p>
   <p xml:id="41" begin="00:01:09.882" end="00:01:15.254">KIND OF THING HE DID THIS<br/></p>
   <p xml:id="42" begin="00:01:12.284" end="00:01:15.921">WEEKEND WHEN HE TREATED<br/></p>
   <p xml:id="43" begin="00:01:15.387" end="00:01:18.090">INCREDIBLY INSENSITIVE TWEET<br/></p>
   <p xml:id="44" begin="00:01:16.055" end="00:01:20.960">AFTER A WOMAN WAS SHOT ON<br/></p>
   <p xml:id="45" begin="00:01:18.224" end="00:01:21.894">THE STREETS OF CHICAGO.<br/></p>
   <p xml:id="46" begin="00:01:21.093" end="00:01:23.095">&gt;&gt; DWYANE WADE'S COUSIN.<br/></p>
   <p xml:id="47" begin="00:01:22.027" end="00:01:23.596">&gt;&gt; HE TRIES TO TAKE CREDIT<br/></p>
   <p xml:id="48" begin="00:01:23.229" end="00:01:25.130">FOR THESE THINGS.<br/></p>
   <p xml:id="49" begin="00:01:23.729" end="00:01:26.398">DID HE IT AFTER ORLANDO.<br/></p>
   <p xml:id="50" begin="00:01:25.264" end="00:01:27.566">HE DID IT AFTER THIS TRAGEDY<br/></p>
   <p xml:id="51" begin="00:01:26.532" end="00:01:28.167">IN CHICAGO LAST WEEK.<br/></p>
   <p xml:id="52" begin="00:01:27.700" end="00:01:29.201">THIS IS WHAT HE DOES.<br/></p>
   <p xml:id="53" begin="00:01:28.300" end="00:01:31.770">HE THINKS EVERYTHING IS<br/></p>
   <p xml:id="54" begin="00:01:29.335" end="00:01:32.104">ABOUT HIM, HIS POLITICAL<br/></p>
   <p xml:id="55" begin="00:01:31.904" end="00:01:35.140">TUNISM.<br/></p>
   <p xml:id="56" begin="00:01:32.238" end="00:01:35.975">IT SHOWS WHY THE MAN IS<br/></p>
   <p xml:id="57" begin="00:01:35.274" end="00:01:36.709">TEMPERAMENTALLY UNFIT TO BE<br/></p>
   <p xml:id="58" begin="00:01:36.108" end="00:01:37.042">PRESIDENT OF THE UNITED<br/></p>
   <p xml:id="59" begin="00:01:36.842" end="00:01:38.077">STATES.<br/></p>
   <p xml:id="60" begin="00:01:37.176" end="00:01:39.845">&gt;&gt; JOINING US NOW WITH<br/></p>
   <p xml:id="61" begin="00:01:38.210" end="00:01:40.779">REACTION FROM NEW YORK, JUAN<br/></p>
   <p xml:id="62" begin="00:01:39.979" end="00:01:42.014">WILLIAMS, FOX NEWS POLITICAL<br/></p>
   <p xml:id="63" begin="00:01:40.913" end="00:01:43.582">ANALYST AND CO-HOST OF THE<br/></p>
   <p xml:id="64" begin="00:01:42.147" end="00:01:46.919">FIVE AND HERE IN WASHINGTON,<br/></p>
   <p xml:id="65" begin="00:01:43.716" end="00:01:47.586">LISA BOOTH, CONTRIBUTOR FOR<br/></p>
   <p xml:id="66" begin="00:01:47.052" end="00:01:48.787">&quot;THE WASHINGTON EXAMINER.&quot;<br/></p>
   <p xml:id="67" begin="00:01:47.720" end="00:01:49.755">ALL RIGHT, JUAN, LET'S START<br/></p>
   <p xml:id="68" begin="00:01:48.921" end="00:01:51.690">WITH YOU.<br/></p>
   <p xml:id="69" begin="00:01:49.889" end="00:01:52.424">YOUR THOUGHTS ON THE ANTHONY<br/></p>
   <p xml:id="70" begin="00:01:51.824" end="00:01:53.592">WEINER REMARKS BY DONALD<br/></p>
   <p xml:id="71" begin="00:01:52.558" end="00:01:54.460">TRUMP AND WHETHER THAT'S<br/></p>
   <p xml:id="72" begin="00:01:53.726" end="00:01:55.528">FAIR GAME.<br/></p>
   <p xml:id="73" begin="00:01:54.593" end="00:01:55.828">&gt;&gt; I DON'T THINK THAT'S FAIR<br/></p>
   <p xml:id="74" begin="00:01:55.661" end="00:01:56.729">GAME.<br/></p>
   <p xml:id="75" begin="00:01:55.961" end="00:01:57.763">THIS HAS REALLY EVERYTHING<br/></p>
   <p xml:id="76" begin="00:01:56.862" end="00:01:59.298">TO DO WITH THE POWER OF<br/></p>
   <p xml:id="77" begin="00:01:57.897" end="00:02:00.599">DAMAGE TO A FAMILY, A CHILD<br/></p>
   <p xml:id="78" begin="00:01:59.431" end="00:02:02.434">INVOLVED IN ONE OF THE<br/></p>
   <p xml:id="79" begin="00:02:00.733" end="00:02:03.369">PICTURES THAT WEINER WAS<br/></p>
   <p xml:id="80" begin="00:02:02.568" end="00:02:05.137">TEXTING.<br/></p>
   <p xml:id="81" begin="00:02:03.502" end="00:02:06.639">IT'S PRETTY DISPARAGING TO<br/></p>
   <p xml:id="82" begin="00:02:05.271" end="00:02:07.806">HIM AND TO -- DAMAGING TO<br/></p>
   <p xml:id="83" begin="00:02:06.772" end="00:02:09.942">HIS FAMILY.<br/></p>
   <p xml:id="84" begin="00:02:07.940" end="00:02:10.242">IT'S A FAMILY FALLING APART,<br/></p>
   <p xml:id="85" begin="00:02:10.075" end="00:02:11.310">BRIT.<br/></p>
   <p xml:id="86" begin="00:02:10.376" end="00:02:12.711">I THINK IT ALSO HAS TO DO<br/></p>
   <p xml:id="87" begin="00:02:11.443" end="00:02:14.513">WITH THE POWER OF SEXTING<br/></p>
   <p xml:id="88" begin="00:02:12.845" end="00:02:16.048">AND SENDING NUDE PICTURES OF<br/></p>
   <p xml:id="89" begin="00:02:14.647" end="00:02:16.916">YOURSELF AND ALL OF THAT<br/></p>
   <p xml:id="90" begin="00:02:16.181" end="00:02:18.450">JUST TAWDRY STUFF.<br/></p>
   <p xml:id="91" begin="00:02:17.049" end="00:02:19.652">AND FOR A MAN WHO HAS BEEN<br/></p>
   <p xml:id="92" begin="00:02:18.584" end="00:02:21.320">THROUGH TWO DIVORCES, DONALD<br/></p>
   <p xml:id="93" begin="00:02:19.785" end="00:02:22.955">TRUMP, YOU WOULD THINK THAT<br/></p>
   <p xml:id="94" begin="00:02:21.453" end="00:02:25.224">HE WOULD APPRECIATE THE<br/></p>
   <p xml:id="95" begin="00:02:23.088" end="00:02:25.624">TURBULENCE THAT FAMILY IS<br/></p>
   <p xml:id="96" begin="00:02:25.357" end="00:02:26.525">UNDERGOING.<br/></p>
   <p xml:id="97" begin="00:02:25.758" end="00:02:27.326">DOES IT HAVE TO DO WITH<br/></p>
   <p xml:id="98" begin="00:02:26.659" end="00:02:27.593">POLITICS?<br/></p>
   <p xml:id="99" begin="00:02:27.459" end="00:02:28.661">NO.<br/></p>
   <p xml:id="100" begin="00:02:27.726" end="00:02:30.296">IT DOESN'T HAVE ANYTHING TO<br/></p>
   <p xml:id="101" begin="00:02:28.794" end="00:02:31.096">DO WITH POLITICS.<br/></p>
   <p xml:id="102" begin="00:02:30.429" end="00:02:32.097">NATIONAL SECURITY?<br/></p>
   <p xml:id="103" begin="00:02:31.230" end="00:02:33.532">I DON'T THINK ANTHONY WEINER<br/></p>
   <p xml:id="104" begin="00:02:32.231" end="00:02:34.199">HAS ACCESS TO NATIONAL<br/></p>
   <p xml:id="105" begin="00:02:33.666" end="00:02:34.767">SECURITY INFORMATION COMING<br/></p>
   <p xml:id="106" begin="00:02:34.333" end="00:02:36.235">FROM HILLARY CLINTON.<br/></p>
   <p xml:id="107" begin="00:02:34.900" end="00:02:39.338">THAT'S WHERE I THINK HE WENT<br/></p>
   <p xml:id="108" begin="00:02:36.368" end="00:02:40.839">OVER THE LINE AND SUGGESTS,<br/></p>
   <p xml:id="109" begin="00:02:39.471" end="00:02:41.941">AS JOE DID THAT IT HAS TO DO<br/></p>
   <p xml:id="110" begin="00:02:40.973" end="00:02:43.108">WITH HIS OWN VIEW THAT<br/></p>
   <p xml:id="111" begin="00:02:42.074" end="00:02:44.310">EVERYTHING IS ABOUT HIM, I<br/></p>
   <p xml:id="112" begin="00:02:43.242" end="00:02:45.578">TOLD YOU SO.<br/></p>
   <p xml:id="113" begin="00:02:44.443" end="00:02:46.979">I KNEW WEINER, I TOLD YOU<br/></p>
   <p xml:id="114" begin="00:02:45.711" end="00:02:48.147">ABOUT THE DAMAGE IN THE<br/></p>
   <p xml:id="115" begin="00:02:47.112" end="00:02:48.514">BLACK COMMUNITY AND THE<br/></p>
   <p xml:id="116" begin="00:02:48.280" end="00:02:49.381">SHOOTINGS.<br/></p>
   <p xml:id="117" begin="00:02:48.647" end="00:02:51.050">IT'S ALL ABOUT TRUMP.<br/></p>
   <p xml:id="118" begin="00:02:49.515" end="00:02:52.551">AT SOME POINT I THINK EVEN<br/></p>
   <p xml:id="119" begin="00:02:51.183" end="00:02:54.787">HIS MOST ARDENT SUPPORTERS<br/></p>
   <p xml:id="120" begin="00:02:52.685" end="00:02:56.355">WOULD SAY COME ON, DONALD,<br/></p>
   <p xml:id="121" begin="00:02:54.920" end="00:02:57.923">LET'S SHOW A LITTLE PERSONAL<br/></p>
   <p xml:id="122" begin="00:02:56.488" end="00:02:58.257">EMPATHY HERE.<br/></p>
   <p xml:id="123" begin="00:02:58.057" end="00:02:59.124">&gt;&gt; LISA?<br/></p>
   <p xml:id="124" begin="00:02:58.390" end="00:03:00.225">&gt;&gt; YEAH.<br/></p>
   <p xml:id="125" begin="00:02:59.258" end="00:03:01.594">I THINK HUMA ABEDIN IS<br/></p>
   <p xml:id="126" begin="00:03:00.359" end="00:03:02.161">CERTAINLY A FAIR GAME IN<br/></p>
   <p xml:id="127" begin="00:03:01.727" end="00:03:04.096">THIS ELECTION.<br/></p>
   <p xml:id="128" begin="00:03:02.294" end="00:03:05.864">BUT I THINK TRYING TO TIE<br/></p>
   <p xml:id="129" begin="00:03:04.229" end="00:03:07.333">ALL THIS TOGETHER AND MOST<br/></p>
   <p xml:id="130" begin="00:03:05.998" end="00:03:08.901">SPECIFICALLY USING HER<br/></p>
   <p xml:id="131" begin="00:03:07.466" end="00:03:11.136">DIVORCE IN IT AS WELL AS A<br/></p>
   <p xml:id="132" begin="00:03:09.034" end="00:03:11.937">LITTLE BIT OF OUT OF BOUNDS<br/></p>
   <p xml:id="133" begin="00:03:11.270" end="00:03:13.772">HERE, THERE IS PLENTY OF<br/></p>
   <p xml:id="134" begin="00:03:12.071" end="00:03:14.873">INFORMATION FOR HIM TO GO<br/></p>
   <p xml:id="135" begin="00:03:13.906" end="00:03:15.207">AFTER HUMA EXCLUSIVE OF THE<br/></p>
   <p xml:id="136" begin="00:03:15.007" end="00:03:16.542">DIVORCE.<br/></p>
   <p xml:id="137" begin="00:03:15.341" end="00:03:18.110">YOU LOOK AT THE FACT THAT<br/></p>
   <p xml:id="138" begin="00:03:16.675" end="00:03:18.744">SHE WAS WORKING AT THE<br/></p>
   <p xml:id="139" begin="00:03:18.243" end="00:03:21.313">CLINTON FOUNDATION AT THE<br/></p>
   <p xml:id="140" begin="00:03:18.877" end="00:03:24.483">STATE DEPARTMENT AND ALSO<br/></p>
   <p xml:id="141" begin="00:03:21.447" end="00:03:25.651">TENAO WHICH WAS RUN BY THE<br/></p>
   <p xml:id="142" begin="00:03:24.617" end="00:03:26.819">BAND WHO WAS THE CLINTON<br/></p>
   <p xml:id="143" begin="00:03:25.784" end="00:03:29.188">FOUNDATION OFFICIAL ALL AT<br/></p>
   <p xml:id="144" begin="00:03:26.952" end="00:03:29.955">THE SAME TIME WHICH SEEMS TO<br/></p>
   <p xml:id="145" begin="00:03:29.321" end="00:03:31.357">HAVE BEEN SUCCESSFUL OF<br/></p>
   <p xml:id="146" begin="00:03:30.089" end="00:03:31.924">SELLING ACCESS TO HILLARY<br/></p>
   <p xml:id="147" begin="00:03:31.490" end="00:03:32.591">CLINTON.<br/></p>
   <p xml:id="148" begin="00:03:32.057" end="00:03:35.027">ESPECIALLY WITH THE REPORT<br/></p>
   <p xml:id="149" begin="00:03:32.725" end="00:03:36.228">TODAY THAT OF THOSE 15,000<br/></p>
   <p xml:id="150" begin="00:03:35.160" end="00:03:37.096">EMAILS HILLARY CLINTON<br/></p>
   <p xml:id="151" begin="00:03:36.362" end="00:03:39.365">ALLEGEDLY, ALL THE EMAILS<br/></p>
   <p xml:id="152" begin="00:03:37.229" end="00:03:40.199">THAT SHE HAD TURNED OVER,<br/></p>
   <p xml:id="153" begin="00:03:39.498" end="00:03:41.300">THERE IS ALSO BENGHAZI<br/></p>
   <p xml:id="154" begin="00:03:40.332" end="00:03:44.770">EMAILS ON THERE AS WELL<br/></p>
   <p xml:id="155" begin="00:03:41.433" end="00:03:47.006">WHICH SHE HAD LIED ABOUT.<br/></p>
   <p xml:id="156" begin="00:03:44.903" end="00:03:48.107">&gt;&gt; TRUMP'S POINT IS SHE HAD<br/></p>
   <p xml:id="157" begin="00:03:47.139" end="00:03:48.474">ACCESS TO CLASSIFIED<br/></p>
   <p xml:id="158" begin="00:03:48.240" end="00:03:49.375">MATERIAL.<br/></p>
   <p xml:id="159" begin="00:03:48.607" end="00:03:50.109">SUPPOSEDLY SHE LEFT IT ON<br/></p>
   <p xml:id="160" begin="00:03:49.508" end="00:03:51.644">THE CAR SEAT.<br/></p>
   <p xml:id="161" begin="00:03:50.242" end="00:03:51.977">SHE HAS LEFT IT OTHER<br/></p>
   <p xml:id="162" begin="00:03:51.777" end="00:03:53.912">PLACES.<br/></p>
   <p xml:id="163" begin="00:03:52.111" end="00:03:54.680">AND SOMEHOW BRINGING ANTHONY<br/></p>
   <p xml:id="164" begin="00:03:54.046" end="00:03:56.415">WEINER INTO IT.<br/></p>
   <p xml:id="165" begin="00:03:54.813" end="00:03:57.249">&gt;&gt; I MEAN, YEAH.<br/></p>
   <p xml:id="166" begin="00:03:56.548" end="00:03:59.084">POTENTIALLY IN THE SENSE<br/></p>
   <p xml:id="167" begin="00:03:57.383" end="00:03:59.918">THAT HUMA DID SAY THAT SHE<br/></p>
   <p xml:id="168" begin="00:03:59.218" end="00:04:00.519">HAD LEFT CLASSIFIED<br/></p>
   <p xml:id="169" begin="00:04:00.052" end="00:04:02.321">INFORMATION IN THE FRONT<br/></p>
   <p xml:id="170" begin="00:04:00.653" end="00:04:03.689">SEAT OF A TRAVEL CAR, I<br/></p>
   <p xml:id="171" begin="00:04:02.454" end="00:04:05.591">BELIEVE; SO, YES, I BELIEVE<br/></p>
   <p xml:id="172" begin="00:04:03.822" end="00:04:06.692">IN THAT SENSE POTENTIALLY<br/></p>
   <p xml:id="173" begin="00:04:05.724" end="00:04:08.627">THERE IS A TIE THERE IF WE<br/></p>
   <p xml:id="174" begin="00:04:06.825" end="00:04:09.695">ARE HAVING TO DO ALL OF THIS<br/></p>
   <p xml:id="175" begin="00:04:08.761" end="00:04:10.529">EXPLAINING IT'S PROBABLY NOT<br/></p>
   <p xml:id="176" begin="00:04:09.828" end="00:04:11.530">A CLEAN POLITICAL HIT.<br/></p>
   <p xml:id="177" begin="00:04:10.663" end="00:04:12.297">IF YOU LOOK AT THE BEST<br/></p>
   <p xml:id="178" begin="00:04:11.664" end="00:04:13.399">POLITICAL HITS THERE IS<br/></p>
   <p xml:id="179" begin="00:04:12.431" end="00:04:14.166">SOMETHING WHERE YOU DON'T<br/></p>
   <p xml:id="180" begin="00:04:13.532" end="00:04:15.834">HAVE TO DO THIS TIEING OF<br/></p>
   <p xml:id="181" begin="00:04:14.299" end="00:04:16.602">THE DOTS THAT WE JUST DID.<br/></p>
   <p xml:id="182" begin="00:04:15.968" end="00:04:18.337">THE BEST POLITICAL HITS<br/></p>
   <p xml:id="183" begin="00:04:16.735" end="00:04:18.937">WOULD BE GOING AFTER HUMA<br/></p>
   <p xml:id="184" begin="00:04:18.470" end="00:04:19.605">BASED ON THE INFORMATION<br/></p>
   <p xml:id="185" begin="00:04:19.071" end="00:04:21.607">THAT WE ALREADY HAVE.<br/></p>
   <p xml:id="186" begin="00:04:19.738" end="00:04:23.375">THE FACT THAT INFORMATION<br/></p>
   <p xml:id="187" begin="00:04:21.740" end="00:04:24.143">ABOUT HER HER EMAILS ARE<br/></p>
   <p xml:id="188" begin="00:04:23.509" end="00:04:25.711">SUBPOENAED BY THE FBI.<br/></p>
   <p xml:id="189" begin="00:04:24.276" end="00:04:26.545">THAT SHE WAS UNDER<br/></p>
   <p xml:id="190" begin="00:04:25.844" end="00:04:28.080">INVESTIGATION BY THE FBI.<br/></p>
   <p xml:id="191" begin="00:04:26.679" end="00:04:29.148">THAT SHE HAD A HAND WORKING<br/></p>
   <p xml:id="192" begin="00:04:28.213" end="00:04:32.117">AT THE STATE DEPARTMENT, THE<br/></p>
   <p xml:id="193" begin="00:04:29.281" end="00:04:32.718">CLINTON FOUNDATION, AND<br/></p>
   <p xml:id="194" begin="00:04:32.251" end="00:04:35.254">TENAO.<br/></p>
   <p xml:id="195" begin="00:04:32.851" end="00:04:39.758">SO, YES, LET'S EXPLORE HER<br/></p>
   <p xml:id="196" begin="00:04:35.387" end="00:04:40.726">ROLE IN THIS BUT LET'S LEAVE<br/></p>
   <p xml:id="197" begin="00:04:39.892" end="00:04:41.894">THE OUT OF IT.<br/></p>
   <p xml:id="198" begin="00:04:40.859" end="00:04:42.795">&gt;&gt; TRYING TO EXPAND DONALD<br/></p>
   <p xml:id="199" begin="00:04:42.027" end="00:04:44.263">TRUMP'S BASE SO HE CAN WIN<br/></p>
   <p xml:id="200" begin="00:04:42.928" end="00:04:45.698">THIS ELECTION, YOU ARE<br/></p>
   <p xml:id="201" begin="00:04:44.396" end="00:04:47.700">LOOKING AT A LOT OF PEOPLE<br/></p>
   <p xml:id="202" begin="00:04:45.831" end="00:04:48.300">WHO ARE FIRST OF ALL,<br/></p>
   <p xml:id="203" begin="00:04:47.833" end="00:04:49.868">CONSOLIDATING REPUBLICAN<br/></p>
   <p xml:id="204" begin="00:04:48.434" end="00:04:50.869">VOTES BUT LARGELY WHITE,<br/></p>
   <p xml:id="205" begin="00:04:50.002" end="00:04:52.504">REPUBLICAN WOMEN WHO HAVE ON<br/></p>
   <p xml:id="206" begin="00:04:51.003" end="00:04:54.306">THE FENCE ABOUT TRUMP AND A<br/></p>
   <p xml:id="207" begin="00:04:52.638" end="00:04:54.940">LOT OF HIS LANGUAGE AND<br/></p>
   <p xml:id="208" begin="00:04:54.440" end="00:04:57.209">SPECIFICALLY ABOUT WOMEN.<br/></p>
   <p xml:id="209" begin="00:04:55.074" end="00:04:57.976">SO FOR HIM TO GO AFTER A<br/></p>
   <p xml:id="210" begin="00:04:57.342" end="00:04:59.745">WOMAN AT THE MOMENT OF<br/></p>
   <p xml:id="211" begin="00:04:58.110" end="00:05:01.013">PERSONAL TROUBLE, I DON'T<br/></p>
   <p xml:id="212" begin="00:04:59.878" end="00:05:02.715">THINK IT'S HELPFUL.<br/></p>
  </div>
 </body>
</tt>
