<?xml version="1.0" encoding="UTF-8"?>
<tt xml:lang="en" xmlns="http://www.w3.org/ns/ttml">
 <head>
  <metadata xmlns:ttm="http://www.w3.org/ns/ttml#metadata">
   <ttm:title>ccdata</ttm:title>
  </metadata>
 </head>
 <body>
  <div>
   <p xml:id="1" begin="00:00:06.035" end="00:00:07.002">&gt;&gt; Bill: PERSONAL STORY</p>
   <p xml:id="2" begin="00:00:06.635" end="00:00:08.971">SEGMENT TONIGHT.</p>
   <p xml:id="3" begin="00:00:07.136" end="00:00:10.773">AN AMAZING SITUATION AT FORT</p>
   <p xml:id="4" begin="00:00:09.104" end="00:00:13.576">CAMPBELL, KENTUCKY.</p>
   <p xml:id="5" begin="00:00:10.906" end="00:00:16.579">SERGEANT CHARLES GUITHAN AND</p>
   <p xml:id="6" begin="00:00:13.709" end="00:00:20.082">HIS WIFE KAYLA ARE THE PROUD</p>
   <p xml:id="7" begin="00:00:16.712" end="00:00:21.484">PARENTS OF QUADRUPLETS ON</p>
   <p xml:id="8" begin="00:00:20.216" end="00:00:22.218">SEPTEMBER 30TH WITHOUT</p>
   <p xml:id="9" begin="00:00:21.617" end="00:00:24.086">FERTILITY TREATMENT.</p>
   <p xml:id="10" begin="00:00:22.351" end="00:00:24.420">THE BABIES ARE SMALL BUT</p>
   <p xml:id="11" begin="00:00:24.220" end="00:00:30.393">HEALTHY.</p>
   <p xml:id="12" begin="00:00:24.553" end="00:00:29.792">THE SAME CANNOT BE SAME</p>
   <p xml:id="13" begin="00:00:29.792" end="00:00:29.825">THE SAME CANNOT BE SAIE</p>
   <p xml:id="14" begin="00:00:29.825" end="00:00:31.227">THE SAME CANNOT BE SAID FOR</p>
   <p xml:id="15" begin="00:00:30.526" end="00:00:32.795">THE MOM.</p>
   <p xml:id="16" begin="00:00:31.360" end="00:00:34.163">&gt;&gt; WE LITERALLY GOT MARRIED</p>
   <p xml:id="17" begin="00:00:32.928" end="00:00:35.398">LAST YEAR AND THEN WE FOUND</p>
   <p xml:id="18" begin="00:00:34.296" end="00:00:37.433">OUT LIKE A COUPLE DAYS</p>
   <p xml:id="19" begin="00:00:35.531" end="00:00:40.536">BEFORE THAT BEFORE MY 29TH</p>
   <p xml:id="20" begin="00:00:37.566" end="00:00:50.646">BIRTHDAY THAT MY BIOPSY CAME</p>
   <p xml:id="21" begin="00:00:40.669" end="00:00:52.048">BACK AS HODGKIN'S DIAGNOSIS.</p>
   <p xml:id="22" begin="00:00:50.780" end="00:00:53.349">&gt;&gt; I WAS TOLD I WAS IN</p>
   <p xml:id="23" begin="00:00:52.181" end="00:00:54.483">REMISSION SO WE WERE REALLY</p>
   <p xml:id="24" begin="00:00:53.482" end="00:00:56.285">EXCITED ABOUT THAT IN JUNE</p>
   <p xml:id="25" begin="00:00:54.617" end="00:00:59.422">WE FOUND OUT WE WERE</p>
   <p xml:id="26" begin="00:00:56.419" end="00:01:00.556">PREGNANT WITH QUADRUPLETS SO</p>
   <p xml:id="27" begin="00:00:59.555" end="00:01:01.824">REALLY LIKE LESS THAN A</p>
   <p xml:id="28" begin="00:01:00.690" end="00:01:02.525">MONTH LATER OUR LIFE CHANGED</p>
   <p xml:id="29" begin="00:01:01.958" end="00:01:04.827">IN A POSITIVE WAY.</p>
   <p xml:id="30" begin="00:01:02.658" end="00:01:05.828">&gt;&gt; SO TALK ME THROUGH IT.</p>
   <p xml:id="31" begin="00:01:04.961" end="00:01:06.629">YOU ARE OUT IN THE FIELD AND</p>
   <p xml:id="32" begin="00:01:05.962" end="00:01:08.298">YOU GET THAT CALL.</p>
   <p xml:id="33" begin="00:01:06.763" end="00:01:09.666">&gt;&gt; SHE CALLED ME AND LIKE</p>
   <p xml:id="34" begin="00:01:08.431" end="00:01:11.568">HEY, ARE YOU SITTING DOWN?</p>
   <p xml:id="35" begin="00:01:09.799" end="00:01:13.236">I'M LIKE YEAH, WHAT'S UP?</p>
   <p xml:id="36" begin="00:01:11.701" end="00:01:13.570">SHE SAID SHE IS PREGNANT,</p>
   <p xml:id="37" begin="00:01:13.369" end="00:01:14.671">AWESOME.</p>
   <p xml:id="38" begin="00:01:13.703" end="00:01:18.208">THERE IS FOUR.</p>
   <p xml:id="39" begin="00:01:14.804" end="00:01:18.508">AND I KIND OF WENT INTO,</p>
   <p xml:id="40" begin="00:01:18.341" end="00:01:19.909">WHAT?</p>
   <p xml:id="41" begin="00:01:18.641" end="00:01:20.977">AND SHE IS LIKE YEAH, THERE</p>
   <p xml:id="42" begin="00:01:20.043" end="00:01:25.482">IS FOUR HEART BEATS.</p>
   <p xml:id="43" begin="00:01:21.110" end="00:01:26.616">AND THAT'S WHEN IT KIND OF</p>
   <p xml:id="44" begin="00:01:25.615" end="00:01:29.786">ACTUALLY SENT ME OVER I'M</p>
   <p xml:id="45" begin="00:01:26.749" end="00:01:32.522">KIND OF IN SHOCK RIGHT NOW.</p>
   <p xml:id="46" begin="00:01:29.986" end="00:01:36.826">&gt;&gt; Bill: WITH US NOW JON</p>
   <p xml:id="47" begin="00:01:32.655" end="00:01:45.735">SCOTT FEATURES THE GAY IT'S</p>
   <p xml:id="48" begin="00:01:36.960" end="00:01:41.064">TAN</p>
   <p xml:id="49" begin="00:01:41.064" end="00:01:41.097">GAN</p>
   <p xml:id="50" begin="00:01:41.097" end="00:01:47.170">GAYTAPTAP, RIGHT?</p>
   <p xml:id="51" begin="00:01:45.869" end="00:01:47.904">&gt;&gt; THEY ARE NOT HOME YET.</p>
   <p xml:id="52" begin="00:01:47.303" end="00:01:50.306">DOING WELL IN THE HOSPITAL</p>
   <p xml:id="53" begin="00:01:48.037" end="00:01:51.274">IN THE INTENSIVE CARE.</p>
   <p xml:id="54" begin="00:01:50.507" end="00:01:51.741">&gt;&gt; Bill: THE MOM IS FIGHTING</p>
   <p xml:id="55" begin="00:01:51.408" end="00:01:53.310">FOR HER LIFE.</p>
   <p xml:id="56" begin="00:01:51.875" end="00:01:54.211">&gt;&gt; SHE REALLY IS BUT SHE HAS</p>
   <p xml:id="57" begin="00:01:53.443" end="00:01:56.179">THE BEST ATTITUDE.</p>
   <p xml:id="58" begin="00:01:54.344" end="00:01:58.615">THIS IS THE MOST AMAZING</p>
   <p xml:id="59" begin="00:01:56.313" end="00:01:58.915">COUPLE I HAVE MET IN SOME</p>
   <p xml:id="60" begin="00:01:58.749" end="00:02:00.283">TIME.</p>
   <p xml:id="61" begin="00:01:59.049" end="00:02:02.786">THEY ARE SO POSITIVE DESPITE</p>
   <p xml:id="62" begin="00:02:00.417" end="00:02:03.820">WHAT THEY HAVE GONE THROUGH.</p>
   <p xml:id="63" begin="00:02:02.986" end="00:02:05.989">&gt;&gt; Bill: THE SERGEANT HAS TO</p>
   <p xml:id="64" begin="00:02:03.954" end="00:02:07.357">NOW PAY NOT ONLY FOR THE</p>
   <p xml:id="65" begin="00:02:06.123" end="00:02:09.026">QUADRUPLETS BUT FOR HIS</p>
   <p xml:id="66" begin="00:02:07.491" end="00:02:09.359">WIFE'S MEDICAL TREATMENT,</p>
   <p xml:id="67" begin="00:02:09.159" end="00:02:10.160">CORRECT?</p>
   <p xml:id="68" begin="00:02:09.493" end="00:02:11.128">SO IS HE A SERGEANT.</p>
   <p xml:id="69" begin="00:02:10.294" end="00:02:12.029">HE IS A MILITARY GUY.</p>
   <p xml:id="70" begin="00:02:11.261" end="00:02:13.130">&gt;&gt; RIGHT.</p>
   <p xml:id="71" begin="00:02:12.162" end="00:02:13.463">IMAGINE WHAT THEY HAVE GONE</p>
   <p xml:id="72" begin="00:02:13.263" end="00:02:14.598">THROUGH.</p>
   <p xml:id="73" begin="00:02:13.597" end="00:02:15.732">THEY GET MARRIED.</p>
   <p xml:id="74" begin="00:02:14.731" end="00:02:18.168">DAYS AFTER THEIR MARRIAGE,</p>
   <p xml:id="75" begin="00:02:15.866" end="00:02:19.470">SHE GETS DIAGNOSED WITH</p>
   <p xml:id="76" begin="00:02:18.302" end="00:02:20.404">HODGKIN'S, GOES THROUGH FOUR</p>
   <p xml:id="77" begin="00:02:19.603" end="00:02:21.538">MONTHS OF CHEMOTHERAPY.</p>
   <p xml:id="78" begin="00:02:20.537" end="00:02:22.706">THEN IS TOLD SHE WILL</p>
   <p xml:id="79" begin="00:02:21.672" end="00:02:25.342">PROBABLY NEVER HAVE CHILDREN</p>
   <p xml:id="80" begin="00:02:22.840" end="00:02:25.676">AGAIN BECAUSE OF THAT</p>
   <p xml:id="81" begin="00:02:25.476" end="00:02:28.279">PROCESS.</p>
   <p xml:id="82" begin="00:02:25.809" end="00:02:26.343">LO AND</p>
   <p xml:id="83" begin="00:02:26.343" end="00:02:26.377">LOWAND</p>
   <p xml:id="84" begin="00:02:26.377" end="00:02:26.410">LOW AD</p>
   <p xml:id="85" begin="00:02:26.410" end="00:02:30.648">LOW AND BEDEFIES ALL ODDS</p>
   <p xml:id="86" begin="00:02:28.412" end="00:02:33.050">ONE OUT OF 700,000 SHE GETS</p>
   <p xml:id="87" begin="00:02:30.781" end="00:02:34.785">PREGNANT WITH QUADRUPLETS NO</p>
   <p xml:id="88" begin="00:02:33.184" end="00:02:37.521">FERTILITY DRUGS.</p>
   <p xml:id="89" begin="00:02:34.919" end="00:02:38.656">THEN IS REDIAGNOSED WITH</p>
   <p xml:id="90" begin="00:02:37.655" end="00:02:40.024">HODGKIN'S LYMPHOMA AGAIN AND</p>
   <p xml:id="91" begin="00:02:38.789" end="00:02:41.258">HAD TO GIVE BIRTH EARLIER</p>
   <p xml:id="92" begin="00:02:40.157" end="00:02:43.494">THAN SHE HAD HOPE BECAUSE</p>
   <p xml:id="93" begin="00:02:41.392" end="00:02:43.861">SHE HAD TO START CANCER</p>
   <p xml:id="94" begin="00:02:43.627" end="00:02:46.630">TREATMENT.</p>
   <p xml:id="95" begin="00:02:44.061" end="00:02:48.833">&gt;&gt; Bill: THE BABIES WERE</p>
   <p xml:id="96" begin="00:02:46.764" end="00:02:49.834">THREE POUNDS TO TWO POUNDS.</p>
   <p xml:id="97" begin="00:02:48.966" end="00:02:51.702">THEY ARE DOING FINE.</p>
   <p xml:id="98" begin="00:02:49.967" end="00:02:52.570">MY NEPHEW USE ODD TO BE AT</p>
   <p xml:id="99" begin="00:02:51.836" end="00:02:54.071">FORT CAMPBELL IN THE ARMY.</p>
   <p xml:id="100" begin="00:02:52.703" end="00:02:55.606">HE KNOWS PEOPLE WHO KNOW</p>
   <p xml:id="101" begin="00:02:54.205" end="00:02:56.574">THIS FAMILY AND HE SAID, YOU</p>
   <p xml:id="102" begin="00:02:55.740" end="00:02:57.041">KNOW, UNCLE BILL, CAN YOU</p>
   <p xml:id="103" begin="00:02:56.707" end="00:02:58.309">HELP THEM?</p>
   <p xml:id="104" begin="00:02:57.174" end="00:03:00.745">I GAVE THEM TO YOU BECAUSE I</p>
   <p xml:id="105" begin="00:02:58.442" end="00:03:01.145">HAVE KNOWN YOU FOR, WHAT</p>
   <p xml:id="106" begin="00:03:00.878" end="00:03:02.279">SINCE 1850.</p>
   <p xml:id="107" begin="00:03:01.278" end="00:03:03.647">&gt;&gt; SOMETHING LIKE THAT.</p>
   <p xml:id="108" begin="00:03:02.480" end="00:03:05.416">&gt;&gt; Bill: YOU DID A REALLY</p>
   <p xml:id="109" begin="00:03:03.781" end="00:03:06.250">REALLY GOOD JOB IN</p>
   <p xml:id="110" begin="00:03:05.549" end="00:03:07.818">SPOTLIGHTING BECAUSE I HAVE</p>
   <p xml:id="111" begin="00:03:06.383" end="00:03:09.253">NEVER HEARD OF A STORY LIKE</p>
   <p xml:id="112" begin="00:03:07.952" end="00:03:09.553">THIS.</p>
   <p xml:id="113" begin="00:03:09.386" end="00:03:10.621">EVER.</p>
   <p xml:id="114" begin="00:03:09.687" end="00:03:13.124">THIS IS UNIQUE.</p>
   <p xml:id="115" begin="00:03:10.755" end="00:03:15.526">BUT, THE FOLKS CAN HELP THE</p>
   <p xml:id="116" begin="00:03:13.257" end="00:03:15.827">SERGEANT AND KAYLA BY DOING</p>
   <p xml:id="117" begin="00:03:15.660" end="00:03:17.361">WHAT?</p>
   <p xml:id="118" begin="00:03:15.960" end="00:03:19.997">&gt;&gt; WELL, THERE IS A GO FUND</p>
   <p xml:id="119" begin="00:03:17.495" end="00:03:27.738">ME PAGE.</p>
   <p xml:id="120" begin="00:03:20.131" end="00:03:29.373">IT'S PRONOUNCED GAYTAN'S</p>
   <p xml:id="121" begin="00:03:27.872" end="00:03:30.842">QUADRUPLE PREGNANCY.</p>
   <p xml:id="122" begin="00:03:29.507" end="00:03:32.343">GO FUND ME.COM.</p>
   <p xml:id="123" begin="00:03:30.975" end="00:03:33.411">FRIENDS THERE ON THE BASE, I</p>
   <p xml:id="124" begin="00:03:32.477" end="00:03:35.246">MEAN PEOPLE WHO DIDN'T EVEN</p>
   <p xml:id="125" begin="00:03:33.544" end="00:03:37.048">KNOW THIS YOUNG SERGEANT AND</p>
   <p xml:id="126" begin="00:03:35.379" end="00:03:38.249">HIS WIFE UNDERTOOK A DIAPER</p>
   <p xml:id="127" begin="00:03:37.181" end="00:03:39.751">DRIVE AND THEY HAVE GOT A</p>
   <p xml:id="128" begin="00:03:38.383" end="00:03:40.952">YEAR'S WORTH OF DIAPERS BUT</p>
   <p xml:id="129" begin="00:03:39.884" end="00:03:42.620">WITH QUADS YOU WILL GO</p>
   <p xml:id="130" begin="00:03:41.085" end="00:03:45.123">THROUGH A LOT OF DIAPERS AND</p>
   <p xml:id="131" begin="00:03:42.754" end="00:03:46.090">THEN THERE IS COLLEGE.</p>
   <p xml:id="132" begin="00:03:45.323" end="00:03:46.925">&gt;&gt; Bill: PATRIOTIC AMERICAN</p>
   <p xml:id="133" begin="00:03:46.224" end="00:03:48.860">THE SERGEANT DESERVES ALL</p>
   <p xml:id="134" begin="00:03:47.058" end="00:03:50.061">AMERICANS TO CHIP.</p>
   <p xml:id="135" begin="00:03:48.993" end="00:03:53.765">IN WATCH WHAT'S HAPPENING</p>
   <p xml:id="136" begin="00:03:50.195" end="00:03:55.466">NOW AS OPPOSED TO NEXT WEEK</p>
   <p xml:id="137" begin="00:03:53.898" end="00:03:55.733">TOMORROW 11 A.M. AND 2:00</p>
   <p xml:id="138" begin="00:03:55.600" end="00:03:56.401">P.M.</p>
   <p xml:id="139" begin="00:03:55.867" end="00:03:57.835">TWO PARTER.</p>
   <p xml:id="140" begin="00:03:56.534" end="00:03:59.704">&gt;&gt; PEOPLE WILL REALLY ENJOY</p>
  </div>
 </body>
</tt>
