{
    "id": "4912169991001",
    "title": "Miller Time: Presidential pardons",
    "description": "Comedian sounds off",
    "thumbnails": [
        {
            "url": "http://a57.foxnews.com/media2.foxnews.com/BrightCove/694940094001/2016/05/25/640/360/694940094001_4912173133001_00e7ffa0-5ed8-4997-aa38-80dea254188b.jpg",
            "width": 320,
            "height": 240
        }
    ],
    "timestamp": 1464225006,
    "duration": 335,
    "subtitles": {
        "en-us": [
            {
                "url": "http://media2.foxnews.com/BrightCove/694940094001/2016/05/25/694940094001_4912173413001_captions.dfxp"
            }
        ]
    },
    "formats": [
        {
            "format_id": "hls-meta",
            "url": "http://foxnews-f.akamaihd.net/i/BrightCove/694940094001/2016/05/25/694940094001_491217,4444001_4912169991001,4478001_4912169991001,6129001_4912169991001,4429001_4912169991001,6107001_4912169991001,.mp4.csmil/master.m3u8",
            "ext": "mp4",
            "protocol": "m3u8",
            "preference": -100,
            "resolution": "multiple",
            "format_note": "Quality selection URL"
        },
        {
            "format_id": "hls-44",
            "url": "http://foxnews-f.akamaihd.net/i/BrightCove/694940094001/2016/05/25/694940094001_491217,4444001_4912169991001,4478001_4912169991001,6129001_4912169991001,4429001_4912169991001,6107001_4912169991001,.mp4.csmil/index_0_a.m3u8",
            "manifest_url": "http://foxnews-f.akamaihd.net/i/BrightCove/694940094001/2016/05/25/694940094001_491217,4444001_4912169991001,4478001_4912169991001,6129001_4912169991001,4429001_4912169991001,6107001_4912169991001,.mp4.csmil/index_0_a.m3u8",
            "tbr": 44,
            "ext": "mp4",
            "fps": null,
            "protocol": "m3u8",
            "preference": null,
            "vcodec": "none",
            "acodec": "mp4a.40.2"
        },
        {
            "format_id": "hls-125",
            "url": "http://foxnews-f.akamaihd.net/i/BrightCove/694940094001/2016/05/25/694940094001_491217,4444001_4912169991001,4478001_4912169991001,6129001_4912169991001,4429001_4912169991001,6107001_4912169991001,.mp4.csmil/index_0_av.m3u8",
            "manifest_url": "http://foxnews-f.akamaihd.net/i/BrightCove/694940094001/2016/05/25/694940094001_491217,4444001_4912169991001,4478001_4912169991001,6129001_4912169991001,4429001_4912169991001,6107001_4912169991001,.mp4.csmil/index_0_av.m3u8",
            "tbr": 125,
            "ext": "mp4",
            "fps": null,
            "protocol": "m3u8",
            "preference": null,
            "width": 320,
            "height": 180,
            "vcodec": "avc1.66.30",
            "acodec": "mp4a.40.2"
        },
        {
            "format_id": "hds-288",
            "url": "http://foxnews-f.akamaihd.net/z/BrightCove/694940094001/2016/05/25/694940094001_491217,6129001_4912169991001,4429001_4912169991001,6107001_4912169991001,4478001_4912169991001,.mp4.csmil/manifest.f4m?hdcore=3.4.0&plugin=aasp-3.4.0.132.124",
            "manifest_url": "http://foxnews-f.akamaihd.net/z/BrightCove/694940094001/2016/05/25/694940094001_491217,6129001_4912169991001,4429001_4912169991001,6107001_4912169991001,4478001_4912169991001,.mp4.csmil/manifest.f4m?hdcore=3.4.0&plugin=aasp-3.4.0.132.124",
            "ext": "flv",
            "tbr": 288,
            "width": null,
            "height": null,
            "vcodec": null,
            "preference": null
        },
        {
            "format_id": "hls-288",
            "url": "http://foxnews-f.akamaihd.net/i/BrightCove/694940094001/2016/05/25/694940094001_491217,4444001_4912169991001,4478001_4912169991001,6129001_4912169991001,4429001_4912169991001,6107001_4912169991001,.mp4.csmil/index_1_av.m3u8",
            "manifest_url": "http://foxnews-f.akamaihd.net/i/BrightCove/694940094001/2016/05/25/694940094001_491217,4444001_4912169991001,4478001_4912169991001,6129001_4912169991001,4429001_4912169991001,6107001_4912169991001,.mp4.csmil/index_1_av.m3u8",
            "tbr": 288,
            "ext": "mp4",
            "fps": null,
            "protocol": "m3u8",
            "preference": null,
            "width": 476,
            "height": 268,
            "vcodec": "avc1.66.30",
            "acodec": "mp4a.40.2"
        },
        {
            "format_id": "hds-453",
            "url": "http://foxnews-f.akamaihd.net/z/BrightCove/694940094001/2016/05/25/694940094001_491217,6129001_4912169991001,4429001_4912169991001,6107001_4912169991001,4478001_4912169991001,.mp4.csmil/manifest.f4m?hdcore=3.4.0&plugin=aasp-3.4.0.132.124",
            "manifest_url": "http://foxnews-f.akamaihd.net/z/BrightCove/694940094001/2016/05/25/694940094001_491217,6129001_4912169991001,4429001_4912169991001,6107001_4912169991001,4478001_4912169991001,.mp4.csmil/manifest.f4m?hdcore=3.4.0&plugin=aasp-3.4.0.132.124",
            "ext": "flv",
            "tbr": 453,
            "width": null,
            "height": null,
            "vcodec": null,
            "preference": null
        },
        {
            "format_id": "hls-453",
            "url": "http://foxnews-f.akamaihd.net/i/BrightCove/694940094001/2016/05/25/694940094001_491217,4444001_4912169991001,4478001_4912169991001,6129001_4912169991001,4429001_4912169991001,6107001_4912169991001,.mp4.csmil/index_2_av.m3u8",
            "manifest_url": "http://foxnews-f.akamaihd.net/i/BrightCove/694940094001/2016/05/25/694940094001_491217,4444001_4912169991001,4478001_4912169991001,6129001_4912169991001,4429001_4912169991001,6107001_4912169991001,.mp4.csmil/index_2_av.m3u8",
            "tbr": 453,
            "ext": "mp4",
            "fps": null,
            "protocol": "m3u8",
            "preference": null,
            "width": 640,
            "height": 360,
            "vcodec": "avc1.66.30",
            "acodec": "mp4a.40.2"
        },
        {
            "format_id": "PDL_LOW",
            "url": "http://media2.foxnews.com/BrightCove/694940094001/2016/05/25/694940094001_4912174478001_4912169991001.mp4",
            "tbr": 500,
            "filesize": 12398276,
            "ext": "mp4"
        },
        {
            "format_id": "PDL_MED_LOW",
            "url": "http://media2.foxnews.com/BrightCove/694940094001/2016/05/25/694940094001_4912176129001_4912169991001.mp4",
            "tbr": 700,
            "filesize": 19300415,
            "ext": "mp4"
        },
        {
            "format_id": "hds-837",
            "url": "http://foxnews-f.akamaihd.net/z/BrightCove/694940094001/2016/05/25/694940094001_491217,6129001_4912169991001,4429001_4912169991001,6107001_4912169991001,4478001_4912169991001,.mp4.csmil/manifest.f4m?hdcore=3.4.0&plugin=aasp-3.4.0.132.124",
            "manifest_url": "http://foxnews-f.akamaihd.net/z/BrightCove/694940094001/2016/05/25/694940094001_491217,6129001_4912169991001,4429001_4912169991001,6107001_4912169991001,4478001_4912169991001,.mp4.csmil/manifest.f4m?hdcore=3.4.0&plugin=aasp-3.4.0.132.124",
            "ext": "flv",
            "tbr": 837,
            "width": null,
            "height": null,
            "vcodec": null,
            "preference": null
        },
        {
            "format_id": "hls-837",
            "url": "http://foxnews-f.akamaihd.net/i/BrightCove/694940094001/2016/05/25/694940094001_491217,4444001_4912169991001,4478001_4912169991001,6129001_4912169991001,4429001_4912169991001,6107001_4912169991001,.mp4.csmil/index_3_av.m3u8",
            "manifest_url": "http://foxnews-f.akamaihd.net/i/BrightCove/694940094001/2016/05/25/694940094001_491217,4444001_4912169991001,4478001_4912169991001,6129001_4912169991001,4429001_4912169991001,6107001_4912169991001,.mp4.csmil/index_3_av.m3u8",
            "tbr": 837,
            "ext": "mp4",
            "fps": null,
            "protocol": "m3u8",
            "preference": null,
            "width": 640,
            "height": 360,
            "vcodec": "avc1.66.30",
            "acodec": "mp4a.40.2"
        },
        {
            "format_id": "PDL_MED",
            "url": "http://media2.foxnews.com/BrightCove/694940094001/2016/05/25/694940094001_4912174429001_4912169991001.mp4",
            "tbr": 1000,
            "filesize": 35378190,
            "ext": "mp4"
        },
        {
            "format_id": "hds-1224",
            "url": "http://foxnews-f.akamaihd.net/z/BrightCove/694940094001/2016/05/25/694940094001_491217,6129001_4912169991001,4429001_4912169991001,6107001_4912169991001,4478001_4912169991001,.mp4.csmil/manifest.f4m?hdcore=3.4.0&plugin=aasp-3.4.0.132.124",
            "manifest_url": "http://foxnews-f.akamaihd.net/z/BrightCove/694940094001/2016/05/25/694940094001_491217,6129001_4912169991001,4429001_4912169991001,6107001_4912169991001,4478001_4912169991001,.mp4.csmil/manifest.f4m?hdcore=3.4.0&plugin=aasp-3.4.0.132.124",
            "ext": "flv",
            "tbr": 1224,
            "width": null,
            "height": null,
            "vcodec": null,
            "preference": null
        },
        {
            "format_id": "hls-1224",
            "url": "http://foxnews-f.akamaihd.net/i/BrightCove/694940094001/2016/05/25/694940094001_491217,4444001_4912169991001,4478001_4912169991001,6129001_4912169991001,4429001_4912169991001,6107001_4912169991001,.mp4.csmil/index_4_av.m3u8",
            "manifest_url": "http://foxnews-f.akamaihd.net/i/BrightCove/694940094001/2016/05/25/694940094001_491217,4444001_4912169991001,4478001_4912169991001,6129001_4912169991001,4429001_4912169991001,6107001_4912169991001,.mp4.csmil/index_4_av.m3u8",
            "tbr": 1224,
            "ext": "mp4",
            "fps": null,
            "protocol": "m3u8",
            "preference": null,
            "width": 640,
            "height": 360,
            "vcodec": "avc1.66.30",
            "acodec": "mp4a.40.2"
        },
        {
            "format_id": "PDL_HIGH",
            "url": "http://media2.foxnews.com/BrightCove/694940094001/2016/05/25/694940094001_4912176107001_4912169991001.mp4",
            "tbr": 1500,
            "filesize": 51602925,
            "ext": "mp4"
        }
    ],
    "extractor": "foxnews",
    "webpage_url": "http://video.foxnews.com/v/4912169991001/",
    "webpage_url_basename": "4912169991001",
    "extractor_key": "FoxNews"
}